README.md
setup.py
openvax_project_template/__init__.py
openvax_project_template.egg-info/PKG-INFO
openvax_project_template.egg-info/SOURCES.txt
openvax_project_template.egg-info/dependency_links.txt
openvax_project_template.egg-info/requires.txt
openvax_project_template.egg-info/top_level.txt